quantile_tree/__init__.py
quantile_tree/base.py
quantile_tree/engine.py
quantile_tree/model.py
quantile_tree/objective.py
quantile_tree/utils.py
quantile_tree-0.1.2.dist-info/METADATA
quantile_tree-0.1.2.dist-info/WHEEL
quantile_tree-0.1.2.dist-info/top_level.txt
quantile_tree-0.1.2.dist-info/RECORD
