Metadata-Version: 2.1
Name: quantile-tree
Version: 0.1.2
Summary: Monotone quantile regressor
Home-page: https://github.com/RektPunk/quantile-tree
Author: RektPunk
Author-email: rektpunk@gmail.com
Classifier: Programming Language :: Python :: 3
Classifier: License :: OSI Approved :: MIT License
Classifier: Operating System :: OS Independent
Requires-Python: >=3.6
Requires-Dist: numpy >=2.0.0
Requires-Dist: pandas >=2.0.0
Requires-Dist: lightgbm >=4.0.0
Requires-Dist: xgboost >=2.0.0
